pjsonpath/__init__.py
pjsonpath/pjsonpath.py
pjsonpath-1.5.dist-info/METADATA
pjsonpath-1.5.dist-info/WHEEL
pjsonpath-1.5.dist-info/top_level.txt
pjsonpath-1.5.dist-info/RECORD
