Metadata-Version: 2.1
Name: pjsonpath
Version: 1.5
Summary: Python查找不限层级Json数据中某个key或者value的路径
Home-page: UNKNOWN
Author: yanqing.wang
Author-email: UNKNOWN
License: UNKNOWN
Platform: UNKNOWN
